scout_mcp/__init__.py
scout_mcp/main.py
scout_mcp/scout_api.py
scout_mcp/server.py
scout_mcp_local-2025.11.4.dist-info/licenses/LICENSE
scout_mcp_local-2025.11.4.dist-info/METADATA
scout_mcp_local-2025.11.4.dist-info/WHEEL
scout_mcp_local-2025.11.4.dist-info/entry_points.txt
scout_mcp_local-2025.11.4.dist-info/top_level.txt
scout_mcp_local-2025.11.4.dist-info/RECORD
