Metadata-Version: 2.4
Name: scout-mcp-local
Version: 2025.11.4
Summary: A local MCP for Scout Monitoring data interactions.
Maintainer-email: Scout Monitoring <support@scoutapm.com>
Requires-Python: >=3.10
License-File: LICENSE
Requires-Dist: httpx>=0.28.1
Requires-Dist: mcp[cli]>=1.13.1
Dynamic: license-file
